Explorer/__init__.py
Explorer/explorer.py
ExplorerFramework-0.1.0.dist-info/LICENSE
ExplorerFramework-0.1.0.dist-info/METADATA
ExplorerFramework-0.1.0.dist-info/WHEEL
ExplorerFramework-0.1.0.dist-info/top_level.txt
ExplorerFramework-0.1.0.dist-info/RECORD
