Metadata-Version: 2.1
Name: ExplorerFramework
Version: 0.1.0
Summary: A python framework for developers alike.
Author-email: Knowing <boxeigit@gmail.com>
Project-URL: Homepage, https://github.com/KnowingXR/Explorer
Project-URL: Bug Tracker, https://github.com/KnowingXR/Explorer/issues
Classifier: Programming Language :: Python :: 3
Classifier: License :: OSI Approved :: MIT License
Classifier: Operating System :: OS Independent
Requires-Python: >=3.7
License-File: LICENSE
